fy_polyfit/__init__.py
fy_polyfit/polyfit.py
fy_polyfit-1.2.2.dist-info/METADATA
fy_polyfit-1.2.2.dist-info/WHEEL
fy_polyfit-1.2.2.dist-info/entry_points.txt
fy_polyfit-1.2.2.dist-info/RECORD
