Metadata-Version: 2.3
Name: fy-polyfit
Version: 1.2.2
Summary: polyfit data use linear and Quadratic
Project-URL: Documentation, https://readthedocs.org
Project-URL: Repository, https://github.com/archeno/polyfit
Project-URL: Issues, https://github.com/archeno/polyfit/issues
Project-URL: Changelog, https://github.com/archeno/polyfit/commits/v1.1.0
Author-email: fengyang <yfeng880@163.com>
Classifier: Development Status :: 4 - Beta
Classifier: Intended Audience :: Developers
Classifier: License :: OSI Approved :: MIT License
Classifier: Programming Language :: Python :: 3.8
Classifier: Topic :: Software Development :: Build Tools
Requires-Python: >=3.8
Requires-Dist: matplotlib
Requires-Dist: numpy
